{
  "project_info": {
    "project_number": "716098796396",
    "project_id": "fastbiteus-ae5ab",
    "storage_bucket": "fastbiteus-ae5ab.appspot.com"
  },
  "client": [
    {
      "client_info": {
        "mobilesdk_app_id": "1:716098796396:android:ee31585d5b07bcb173d149",
        "android_client_info": {
          "package_name": "com.fastbiteus_delivery"
        }
      },
      "oauth_client": [],
      "api_key": [
        {
          "current_key": "AIzaSyCXdQTfHLWrrJLYm2IDcMc-JGKAJ1kC7iM"
        }
      ],
      "services": {
        "appinvite_service": {
          "other_platform_oauth_client": []
        }
      }
    },
    {
      "client_info": {
        "mobilesdk_app_id": "1:716098796396:android:98159a2e470dfdb973d149",
        "android_client_info": {
          "package_name": "com.fastbiteus_restaurant"
        }
      },
      "oauth_client": [],
      "api_key": [
        {
          "current_key": "AIzaSyCXdQTfHLWrrJLYm2IDcMc-JGKAJ1kC7iM"
        }
      ],
      "services": {
        "appinvite_service": {
          "other_platform_oauth_client": []
        }
      }
    },
    {
      "client_info": {
        "mobilesdk_app_id": "1:716098796396:android:5439a7db36328d7e73d149",
        "android_client_info": {
          "package_name": "com.fastbiteus_user"
        }
      },
      "oauth_client": [],
      "api_key": [
        {
          "current_key": "AIzaSyCXdQTfHLWrrJLYm2IDcMc-JGKAJ1kC7iM"
        }
      ],
      "services": {
        "appinvite_service": {
          "other_platform_oauth_client": []
        }
      }
    }
  ],
  "configuration_version": "1"
}